django_cotton/__init__.py
django_cotton/apps.py
django_cotton/compiler_regex.py
django_cotton/cotton_loader.py
django_cotton/exceptions.py
django_cotton/nested_tag_support.py
django_cotton/tag_parser.py
django_cotton/templatetags/__init__.py
django_cotton/templatetags/_component.py
django_cotton/templatetags/_slot.py
django_cotton/templatetags/_vars.py
django_cotton/templatetags/cotton.py
django_cotton/urls.py
django_cotton/utils.py
django_cotton/views.py
django_cotton/wsgi.py
django_cotton-2.6.0.dist-info/METADATA
django_cotton-2.6.0.dist-info/WHEEL
django_cotton-2.6.0.dist-info/licenses/LICENSE
django_cotton-2.6.0.dist-info/RECORD
